PyFeishuGroupBot/__init__.py
PyFeishuGroupBot/template.py
pyfeishugroupbot-0.0.7.dist-info/METADATA
pyfeishugroupbot-0.0.7.dist-info/WHEEL
pyfeishugroupbot-0.0.7.dist-info/top_level.txt
pyfeishugroupbot-0.0.7.dist-info/RECORD
