Metadata-Version: 2.4
Name: PyFeishuGroupBot
Version: 0.0.7
Summary: Python的飞书群组机器人调用方法集合
Home-page: https://github.com/Moxin1044/Py-FeishuGroupBot
Author: Moxin
Author-email: 1044631097@qq.com
License: MIT License
Requires-Dist: requests
Dynamic: author
Dynamic: author-email
Dynamic: description
Dynamic: description-content-type
Dynamic: home-page
Dynamic: license
Dynamic: requires-dist
Dynamic: summary
